ti/__init__.py
ti/constant.py
ti/data_source.py
ti/estimator.py
ti/framework.py
ti/session.py
ti/train_job.py
ti/client/__init__.py
ti/client/cls_client.py
ti/client/cos_client.py
ti/client/monitor_client.py
ti/client/ti_client.py
ti/local/__init__.py
ti/local/session.py
ti/local/container/__init__.py
ti/local/container/compose.py
ti/local/container/training.py
ti/mxnet/__init__.py
ti/mxnet/estimator.py
ti/pytorch/__init__.py
ti/pytorch/estimator.py
ti/sklearn/__init__.py
ti/sklearn/estimator.py
ti/tensorflow/__init__.py
ti/tensorflow/estimator.py
ti/tensorflow/tensorboard.py
ti/utils/__init__.py
ti/utils/common_utils.py
ti/utils/file_utils.py
ti_sdk_python-1.3.30.dist-info/LICENSE
ti_sdk_python-1.3.30.dist-info/METADATA
ti_sdk_python-1.3.30.dist-info/WHEEL
ti_sdk_python-1.3.30.dist-info/top_level.txt
ti_sdk_python-1.3.30.dist-info/RECORD
