Metadata-Version: 2.1
Name: ti-sdk-python
Version: 1.3.30
Summary: Open source library for training and deploying models on TencentCloud TIONE.
Home-page: https://cloud.tencent.com
Author: TencentCloud TIONE
License: Apache License 2.0
Keywords: TencentCloud ML TI AI Training
Platform: UNKNOWN
Requires-Python: >=3
Requires-Dist: numpy (>=1.9.0)
Requires-Dist: protobuf (>=3.1)
Requires-Dist: scipy (>=0.19.0)
Requires-Dist: urllib3 (>=1.21)
Requires-Dist: protobuf3-to-dict (>=0.1.5)
Requires-Dist: docker-compose (>=1.23.0)
Requires-Dist: requests (>=2.20.0)
Requires-Dist: packaging
Requires-Dist: tencentcloud-sdk-python
Requires-Dist: cos-python-sdk-v5
Requires-Dist: coscmd
